behave_pandas/__init__.py
behave_pandas/column_types.py
behave_pandas/parser.py
behave_pandas/printer.py
behave_pandas-0.5.0.dist-info/LICENSE
behave_pandas-0.5.0.dist-info/METADATA
behave_pandas-0.5.0.dist-info/WHEEL
behave_pandas-0.5.0.dist-info/top_level.txt
behave_pandas-0.5.0.dist-info/RECORD
