Metadata-Version: 2.1
Name: behave-pandas
Version: 0.5.0
Summary: Provides helper functions to help converting behave tables into pandas dataframes and vice versa.
Home-page: https://github.com/clembou/behave-pandas
Author: Clément Bouscasse
Author-email: clement.bouscasse@gmail.com
License: MIT
Keywords: behave pandas testing bdd
Classifier: Development Status :: 4 - Beta
Classifier: Programming Language :: Python
Classifier: Programming Language :: Python :: 3
Classifier: Programming Language :: Python :: 3.6
Classifier: Programming Language :: Python :: 3.7
Classifier: Programming Language :: Python :: 3.8
Classifier: Programming Language :: Python :: 3.9
Classifier: Programming Language :: Python :: 3.10
Requires-Python: >=3.6
License-File: LICENSE
Requires-Dist: behave
Requires-Dist: pandas (>=0.21)
Requires-Dist: tabulate
